MANIFEST.in
setup.cfg
setup.py
jsonsubset/__init__.py
jsonsubset/json_parser.pxd
jsonsubset/json_parser.pyx
jsonsubset/subset.pyx
jsonsubset.egg-info/PKG-INFO
jsonsubset.egg-info/SOURCES.txt
jsonsubset.egg-info/dependency_links.txt
jsonsubset.egg-info/requires.txt
jsonsubset.egg-info/top_level.txt
jsonsubset/deps/__init__.py
jsonsubset/deps/xxhash_cython/__init__.py
jsonsubset/deps/xxhash_cython/setup.py
jsonsubset/deps/xxhash_cython/xxhash.pxd
jsonsubset/deps/xxhash_cython/xxhash.pyx
jsonsubset/deps/xxhash_cython/xxHash/xxhash.c
jsonsubset/deps/xxhash_cython/xxHash/xxhash.h