Metadata-Version: 1.1
Name: jsonsubset
Version: 0.1.1
Summary: Extract and parse specific fields from a JSON string 
Home-page: https://github.com/kawmarco/jsonsubset
Author: Marco Kawajiri
Author-email: UNKNOWN
License: MIT license
Keywords: jsonsubset,json,select
Platform: UNKNOWN
Classifier: Development Status :: 4 - Beta
Classifier: Intended Audience :: Developers
Classifier: License :: OSI Approved :: MIT License
Classifier: Natural Language :: English
Classifier: Programming Language :: Cython
Classifier: Programming Language :: Python :: 3
Classifier: Programming Language :: Python :: 3.3
Classifier: Programming Language :: Python :: 3.4
Classifier: Programming Language :: Python :: 3.5
Classifier: Programming Language :: Python :: 3.6
